axreldable/__init__.py
axreldable/printing/__init__.py
axreldable/printing/s_print.py
axreldable-0.2.0.dist-info/METADATA
axreldable-0.2.0.dist-info/WHEEL
axreldable-0.2.0.dist-info/top_level.txt
axreldable-0.2.0.dist-info/RECORD
