Metadata-Version: 2.4
Name: axreldable
Version: 0.2.0
Summary: axreldable python utils
License: MIT License
Project-URL: Repository, https://github.com/axreldable/axreldable_python_lib
Project-URL: Issues, https://github.com/axreldable/axreldable_python_lib/issues
Classifier: Development Status :: 4 - Beta
Classifier: Intended Audience :: Developers
Classifier: Programming Language :: Python :: 3
Classifier: Programming Language :: Python :: 3.11
Requires-Python: >=3.11
Requires-Dist: tabulate~=0.9
Provides-Extra: dev
Requires-Dist: pytest>=7.0.0; extra == "dev"
Requires-Dist: black>=23.0.0; extra == "dev"
Requires-Dist: isort>=5.0.0; extra == "dev"
Requires-Dist: twine; extra == "dev"
Requires-Dist: build; extra == "dev"
